{
    "id": "105091",
    "title": "「阿舍哥」Duncan Robinson降臨臺北車站，現場大秀三分及煮乾麵絕技【圖多】",
    "date": "2023/07/22",
    "topic": "籃球",
    "author_name": "運動喫羊肉",
    "tags": [
        "高國豪",
        "Miamiheat",
        "duncanrobinson",
        "簡廷兆",
        "NBA球員來台"
    ],
    "article-content": [
        "邁阿密熱火超級射手「阿舍哥」Duncan Robinson，本週末以乾麵品牌代言人的身份來到台灣。挾帶著熱火隊打進總冠軍賽的氣勢，以及自身在季後賽屢屢上演的好表現，今日(7/22)活動吸引大批球迷來到臺北車站一賭這位三分神射手的風采。",
        "半個籃球場就架設在臺北車站一樓大廳，Duncan Robinson和PLG球星高國豪、簡廷兆進行三分球大賽。比賽共五個點，每個點3顆球一共15球的機會，Duncan共投進10球拿下勝利，倒數第二球還秀了一手Step back可惜沒進。",
        "三分球大賽結束後就是煮麵時間，親自示範煮一碗乾麵給自己享用，整個畫面非常的奇妙且有趣。",
        "Duncan Robinson展現非常親民的態度，不僅展現球技、親自下廚，也花很多時間和球迷互動、簽名、合影，大約一小時的活動球迷參與得相當過癮。",
        "--------------",
        "歡迎按讚追蹤，分享棒籃、體壇動態與國內外各賽事衝現場觀賽體驗"
    ]
}