{
    "id": "110247",
    "title": "NBA》Joel Embiid受傷後最佳解？ Paul Reed的精準救援",
    "date": "2024/03/19",
    "topic": "籃球",
    "author_name": "運動視界編輯",
    "tags": [
        "費城七六人",
        "Paul Reed"
    ],
    "article-content": [
        "Paul Reed在NBA的四年旅途可說是跌跌盪盪。然而，隨著Joel Embiid的長期缺席，Reed獲得了一些證明自己的機會。",
        "自2024年全明星賽以後，Reed的三分球命中率突飛猛進，三分球命中率一度高達63.6%，場均出手 1.1 次，這樣的進步使他今年的賽季三分球命中率也提高到了40%。",
        "儘管出手次數確實不高，但這種投籃能力卻恰恰是76人隊一整年都在等待的。本賽季初，總教練Nick Nurse表示教練團會更多地考慮讓Reed與Embiid並肩作戰，讓Reed將嘗試從外線輸送火力。不過由於傷病及Reed在賽季中因績效不佳，因此放棄了這一點。然而現在，他不僅嘗試投三分，還投進三分。",
        "大多數人們對於Reed的印象停留在發展聯盟的經歷，在發展聯盟的Reed不僅擁有華麗的數據，而且他的外線投籃也很出色。在兩年的時間裡（24 場比賽），Reed的三分球命中率為 43.6%，場均出手近 4 個三分球。",
        "Reed的投籃基礎養成可以追溯到他在大學的日子，最引人注目的是在他的大二賽季，三分球命中率超過了40%。不過在大三那年，他的表現卻也有所退步，場均近兩次出手命中率為 31%，但他依舊宣布參加NBA 選秀。",
        "時至今日，Reed的投籃似乎終於達到了 NBA 的水平。然而有一張數據圖證明，儘管不是成為明星球員的料，但Reed依舊能在有限出手量的情況下成為一名不錯的射手：",
        "有些人可能會對賽季末的投籃增加不以為然，畢竟這是在有限情況下出手的結果。不過換個角度看，這可能預示著76人在接下來的計畫以及Embiid回歸之後會發生什麼。如果Reed能夠持續以足夠高效的成績命中三分球，或許就能期待看到這種合作關係取得更多進展。",
        "76人隊球迷都知道，從理論上講，能夠外線的火力可能是一個重要的「X因子」，而Reed的投籃能力正好是球隊所需要的。Reed把握了機會證明自己，若他能夠保持穩定，無疑會是76人接下來非常重要的戰力。",
        "【特約編輯 林昌毅／責任編輯 謝一謙】",
        "🔥更多最新 NBA 精選好文："
    ]
}