{
    "id": "115703",
    "title": "《2024-25 芝加哥公牛例行賽戰報》G9 明尼蘇達灰狼單節爆量得分致勝",
    "date": "2024/11/09",
    "topic": "籃球",
    "author_name": "AhUtopian/烏托邦/余大",
    "tags": [
        "Rudygobert",
        "TalenHortonTucker",
        "PatrickWilliams",
        "joshgiddey",
        "DonteDiVicenzo",
        "DalenTerry",
        "BullsTimberWolves",
        "MatasBuzelis",
        "202425芝加哥公牛例行賽戰報"
    ],
    "article-content": [
        "芝加哥公牛終於第一節沒有落後給對手，也連續三節單節都有 30 分以上的進攻火力，與明尼蘇達灰狼進入第四節。",
        "然後，啪，被灰狼單節拿到 45 分，比賽就沒了。",
        "說起來，也沒有什麼太多好去意外或抱怨，連續兩天出賽，然後陣中最具得分破壞力的 Zach LaVine ，以及在前幾場都能過渡比賽進攻銜接的 Lonzo Ball 可能要長期缺陣。",
        "第一節兩隊的三分加起來 11/15 ，但特別的是灰狼一直到了第二節才第一次犯規，而公牛這邊延續上一場，第一節就讓 Matas Buzelis 上場，顯現對 Buzelis 後續正式進入輪替的跡象。",
        "公牛連續四場比賽在禁區得分比例提升，可想而知的，這應該是由於 LaVine 缺陣，更需要 Nikola Vucevic 為首來往裡面得分，但也是連續第四場比賽，包含這場的 66 分，對手都在公牛的禁區取分大於 60 分。",
        "當 Rudy Gobert 能投 11 中 9 拿下 21 分，公牛的問題是什麼不言可喻；同時，這也是 Josh Giddey 本季第一次單場得分未達雙位數。",
        "對於 Donte DiVincenzo 本場的表現，跟在紐約尼克時認識的並沒有差太多，不過在灰狼，即使 Anthony Edwards 跟 Mike Conley 在場，也會讓 DiVincenzo 有不少機會在進攻初期就拿到球。",
        "以灰狼這場輪替時間來看，等於是讓 DiVincenzo 擔任實質的替補控衛，但會搭配 Conley 或 Edwards 來共同分攤。",
        "此外，不知道是剛好這場、還是固定， DiVincenzo 大部分的出手都在左半邊為主，但他的助攻則都是往右手下球時所製造出來的。",
        "隨著 Ball 應該又是因為手腕長期養傷，可以觀察一下哪些人會進來輪替陣容，尤其是在 LaVine 回來後的狀況。",
        "Buzelis 這場也是第一節就替補上場，直接把 Julian Phillips 的上場次序往後擠，兩者雖然不是相同路線的球員，但在目前能夠搬上檯面的功能，重疊性有點高。",
        "Dalen Terry 總是一方面又有那種你覺得這個動作怎麼會出現在 NBA 賽場上的窘況，但又能夠蠻意外地找到對的時機點，創造球權或是撿漏， Terry 在季外做了不少增加肉量，可是看起來本來就不是特別好的協調性，跟肢體間的力量落差又更大。",
        "而 Talen Horten-Tucker 單以表現來說，看起來是最有機會爭取進入輪替陣容的人，不過在 LaVine 歸隊後，應該對於 THT 在場上的需求性會回到趨近於零。",
        "Giddey 這場第一球就以三分球開場，這讓我想說「該不會要大爆發了吧」，不過看到是 Jaden McDaniels 對位到 Giddey ，就想說只要沒有散漫的失誤、以及放棄抵抗，就算是有做到本分。",
        "這場應該算是修正得很好，整場沒有失誤，也蠻能掌握 Gobert 為主、加上 McDaniels 是來防守自己的安排下，灰狼在其他防守區域、對象上的可能情境；而對上 Nar Reid 單防自己時，其中居然有一球選擇運球後後撤步三分。",
        "Patrick Williams 的三分逐漸投回生涯水準，但是 Williams 本季的兩分球命中率 30.6% 低到比三分命中率 37.5% 還低？而且生涯第二年之後，每年兩分球命中率都在下滑。",
        "談到兩分球命中率， Ayo Dosunmu 好像是出手數多少以上，所有公牛球員中兩分球命中率第二高的球員，最高的是Artis Gilmore 。"
    ]
}