{
    "id": "117908",
    "title": "Kyrie Irving倒下後，獨行俠將何去何從？",
    "date": "2025/03/04",
    "topic": "籃球",
    "author_name": "奇人",
    "tags": [
        "季後賽",
        "達拉斯",
        "獨行俠",
        "傷病",
        "Kyrie Irving"
    ],
    "article-content": [
        "本季的獨行俠可謂是聯盟的輿論中心，從季初Luka表現的疲軟，到震碎三觀的世紀大交易，再到犢禁區人手的傷病潮。KI不語，只是默默地扛著球隊前進，直到本日在對陣國王的比賽中，一次切入禁區造成防守犯規後倒在地上久久不起。最後展現「曼巴精神」，將球罰進才在隊友的攙扶下返回更衣室。",
        "本季的獨行俠經歷了風風雨雨，正當所有犢迷翹首以盼AD, Gafford, Lively即將在未來幾週回歸賽場時，本季的神主牌Kyrie Irving卻驀然倒下，可謂是至暗時刻。",
        "接下來還有20場的賽程，犢屆時應會將Max Christie和Kai Jones放上先發，以戰養傷，等到禁區人手健康回歸。而接下來犢的看點就是Christie能否扛起球隊的進攻箭頭，並贏下盡可能多的比賽。同時，本季形同遊魂的Jaden Hardy能否回魂，拯救球隊於水火之中也是一個可以關注的點。",
        "獨行俠在剩餘的比賽中，將會打更多的早攻和攻守轉換，並且憑藉著球隊優良的尺寸、身體素質等優勢在防守端發揮優勢，並且依靠陣容深度在銜階段爭取更多分數，最後在季末爭取一個附加賽的名額。",
        "最後還是希冀KI的傷勢能早日康復，和AD, Lively再次連線完成精彩配合。"
    ]
}